[
    {
        "name": "sessionid",
        "value": "YOUR_SESSION_ID_HERE",
        "domain": ".instagram.com",
        "path": "/",
        "secure": true,
        "httpOnly": true
    },
    {
        "name": "csrftoken",
        "value": "YOUR_CSRF_TOKEN_HERE",
        "domain": ".instagram.com",
        "path": "/",
        "secure": true,
        "httpOnly": false
    },
    {
        "name": "ds_user_id",
        "value": "YOUR_USER_ID_HERE",
        "domain": ".instagram.com",
        "path": "/",
        "secure": true,
        "httpOnly": false
    }
]